{
    "rooms": [
        {
            "ID": 25100,
            "Zone": 251,
            "Name": "Aboard the Chaos ship.",
            "Description": "Flashing yellow lights line this corridor accompanied by loud sirens. Bulkheads\r\r\r\r\n\rcan be seen above you scared and seared as if a huge battle took place here.\r\r\r\r\n\rCold air blasts your face as it streams out of a busted pipe. Small port holes\r\r\r\r\n\rlet you look out into the high atomsphere of Macragge. \r\r\r\r\n\r",
            "Bits": [
                "INDOORS",
                "NOTELEPORT",
                "NORELOCATE",
                "NOQUIT"
            ],
            "Sector": "INSIDE",
            "Exits": [
                {
                    "Direction": "North",
                    "Description": "",
                    "Keywords": [],
                    "DoorFlags": null,
                    "KeyID": -1,
                    "Destination": 25107
                },
                {
                    "Direction": "East",
                    "Description": "",
                    "Keywords": [],
                    "DoorFlags": null,
                    "KeyID": -1,
                    "Destination": 25101
                }
            ],
            "ExtraDescs": null
        },
        {
            "ID": 25101,
            "Zone": 251,
            "Name": "Aboard the Chaos ship.",
            "Description": "Flashing yellow lights line this corridor accompanied by loud sirens. Yellow\r\r\r\r\n\rcaution stripes can be seen on the walls with hoses and tubes. Cold air blasts\r\r\r\r\n\ryour face as it streams out of a busted pipe. Steel grates line the floor,\r\r\r\r\n\rsome like as if they have been eaten through by acid. \r\r\r\r\n\r",
            "Bits": [
                "INDOORS",
                "NOTELEPORT",
                "NORELOCATE",
                "NOQUIT"
            ],
            "Sector": "INSIDE",
            "Exits": [
                {
                    "Direction": "East",
                    "Description": "",
                    "Keywords": [],
                    "DoorFlags": null,
                    "KeyID": -1,
                    "Destination": 25102
                },
                {
                    "Direction": "West",
                    "Description": "",
                    "Keywords": [],
                    "DoorFlags": null,
                    "KeyID": -1,
                    "Destination": 25100
                }
            ],
            "ExtraDescs": null
        },
        {
            "ID": 25102,
            "Zone": 251,
            "Name": "Aboard the Chaos ship.",
            "Description": "Flashing yellow lights line this corridor accompanied by loud sirens. Busted\r\r\r\r\n\rhoses and pipes spray steam and smoke into the room. The air in this room is\r\r\r\r\n\rso thin you can hardly breathe. Bodies of Imperial space marines lay strewn\r\r\r\r\n\racross the floor. \r\r\r\r\n\r",
            "Bits": [
                "INDOORS",
                "NOTELEPORT",
                "NORELOCATE",
                "NOQUIT"
            ],
            "Sector": "INSIDE",
            "Exits": [
                {
                    "Direction": "East",
                    "Description": "",
                    "Keywords": [],
                    "DoorFlags": null,
                    "KeyID": -1,
                    "Destination": 25103
                },
                {
                    "Direction": "West",
                    "Description": "",
                    "Keywords": [],
                    "DoorFlags": null,
                    "KeyID": -1,
                    "Destination": 25101
                }
            ],
            "ExtraDescs": null
        },
        {
            "ID": 25103,
            "Zone": 251,
            "Name": "Aboard the Chaos ship.",
            "Description": "Flashing yellow lights line this corridor accompanied by loud sirens. Demonic\r\r\r\r\n\rfaces and pagan carvings can be seen on all the walls in this room. The air\r\r\r\r\n\rhere smells like sulfur and your eyes can not stop from watering. Bodies of\r\r\r\r\n\rImperial space marines lay strewn across the floor. \r\r\r\r\n\r",
            "Bits": [
                "INDOORS",
                "NOTELEPORT",
                "NORELOCATE",
                "NOQUIT"
            ],
            "Sector": "INSIDE",
            "Exits": [
                {
                    "Direction": "North",
                    "Description": "",
                    "Keywords": [],
                    "DoorFlags": null,
                    "KeyID": -1,
                    "Destination": 25108
                },
                {
                    "Direction": "East",
                    "Description": "",
                    "Keywords": [],
                    "DoorFlags": null,
                    "KeyID": -1,
                    "Destination": 25104
                },
                {
                    "Direction": "West",
                    "Description": "",
                    "Keywords": [],
                    "DoorFlags": null,
                    "KeyID": -1,
                    "Destination": 25102
                }
            ],
            "ExtraDescs": null
        },
        {
            "ID": 25104,
            "Zone": 251,
            "Name": "Aboard the Chaos ship.",
            "Description": "Flashing yellow lights line this corridor accompanied by loud sirens. Bulkheads\r\r\r\r\n\rcan be seen above you scared and seared as if a huge battle took place here.\r\r\r\r\n\rThe air here smells like sulfur and your eyes can not stop from watering.\r\r\r\r\n\rSteel grates line the floor, some like as if they have been eaten through by\r\r\r\r\n\racid. \r\r\r\r\n\r",
            "Bits": [
                "INDOORS",
                "NOTELEPORT",
                "NORELOCATE",
                "NOQUIT"
            ],
            "Sector": "INSIDE",
            "Exits": [
                {
                    "Direction": "East",
                    "Description": "",
                    "Keywords": [],
                    "DoorFlags": null,
                    "KeyID": -1,
                    "Destination": 25105
                },
                {
                    "Direction": "West",
                    "Description": "",
                    "Keywords": [],
                    "DoorFlags": null,
                    "KeyID": -1,
                    "Destination": 25103
                }
            ],
            "ExtraDescs": null
        },
        {
            "ID": 25105,
            "Zone": 251,
            "Name": "Aboard the Chaos ship.",
            "Description": "Flashing yellow lights line this corridor accompanied by loud sirens. Busted\r\r\r\r\n\rhoses and pipes spray steam and smoke into the room. The heat in this room is\r\r\r\r\n\runbelievable. The walls shimmer infront of you from the heat. Bodies of\r\r\r\r\n\rImperial space marines lay strewn across the floor. \r\r\r\r\n\r",
            "Bits": [
                "INDOORS",
                "NOTELEPORT",
                "NORELOCATE",
                "NOQUIT"
            ],
            "Sector": "INSIDE",
            "Exits": [
                {
                    "Direction": "North",
                    "Description": "",
                    "Keywords": [],
                    "DoorFlags": null,
                    "KeyID": -1,
                    "Destination": 25109
                },
                {
                    "Direction": "East",
                    "Description": "",
                    "Keywords": [],
                    "DoorFlags": null,
                    "KeyID": -1,
                    "Destination": 25106
                },
                {
                    "Direction": "West",
                    "Description": "",
                    "Keywords": [],
                    "DoorFlags": null,
                    "KeyID": -1,
                    "Destination": 25104
                }
            ],
            "ExtraDescs": null
        },
        {
            "ID": 25106,
            "Zone": 251,
            "Name": "Aboard the Chaos ship.",
            "Description": "Flashing yellow lights line this corridor accompanied by loud sirens. Yellow\r\r\r\r\n\rcaution stripes can be seen on the walls with hoses and tubes. Small port\r\r\r\r\n\rholes let you look out into the high atomsphere of Macragge. The heat in this\r\r\r\r\n\rroom is unbelievable. The walls shimmer infront of you from the heat. \r\r\r\r\n\r",
            "Bits": [
                "INDOORS",
                "NOTELEPORT",
                "NORELOCATE",
                "NOQUIT"
            ],
            "Sector": "INSIDE",
            "Exits": [
                {
                    "Direction": "West",
                    "Description": "",
                    "Keywords": [],
                    "DoorFlags": null,
                    "KeyID": -1,
                    "Destination": 25105
                },
                {
                    "Direction": "Northeast",
                    "Description": "",
                    "Keywords": [],
                    "DoorFlags": null,
                    "KeyID": -1,
                    "Destination": 25110
                }
            ],
            "ExtraDescs": null
        },
        {
            "ID": 25107,
            "Zone": 251,
            "Name": "Aboard the Chaos ship.",
            "Description": "Flashing yellow lights line this corridor accompanied by loud sirens. Yellow\r\r\r\r\n\rcaution stripes can be seen on the walls with hoses and tubes. Steel grates\r\r\r\r\n\rline the floor, some like as if they have been eaten through by acid. The heat\r\r\r\r\n\rin this room is unbelievable. The walls shimmer infront of you from the heat. \r\r\r\r\n\r",
            "Bits": [
                "INDOORS",
                "NOTELEPORT",
                "NORELOCATE",
                "NOQUIT"
            ],
            "Sector": "INSIDE",
            "Exits": [
                {
                    "Direction": "North",
                    "Description": "",
                    "Keywords": [],
                    "DoorFlags": null,
                    "KeyID": -1,
                    "Destination": 25112
                },
                {
                    "Direction": "South",
                    "Description": "",
                    "Keywords": [],
                    "DoorFlags": null,
                    "KeyID": -1,
                    "Destination": 25100
                }
            ],
            "ExtraDescs": null
        },
        {
            "ID": 25108,
            "Zone": 251,
            "Name": "Aboard the Chaos ship.",
            "Description": "Flashing yellow lights line this corridor accompanied by loud sirens. Busted\r\r\r\r\n\rhoses and pipes spray steam and smoke into the room. Small port holes let you\r\r\r\r\n\rlook out into the high atomsphere of Macragge. Cold air blasts your face as it\r\r\r\r\n\rstreams out of a busted pipe. \r\r\r\r\n\r",
            "Bits": [
                "INDOORS",
                "NOTELEPORT",
                "NORELOCATE",
                "NOQUIT"
            ],
            "Sector": "INSIDE",
            "Exits": [
                {
                    "Direction": "North",
                    "Description": "",
                    "Keywords": [],
                    "DoorFlags": null,
                    "KeyID": -1,
                    "Destination": 25114
                },
                {
                    "Direction": "South",
                    "Description": "",
                    "Keywords": [],
                    "DoorFlags": null,
                    "KeyID": -1,
                    "Destination": 25103
                }
            ],
            "ExtraDescs": null
        },
        {
            "ID": 25109,
            "Zone": 251,
            "Name": "Aboard the Chaos ship.",
            "Description": "Flashing yellow lights line this corridor accompanied by loud sirens. Soot\r\r\r\r\n\rcovers the floor with foot prints going into and out of the room. Green slime\r\r\r\r\n\rdrips from the walls eating it's way through the floor as it hits. The heat in\r\r\r\r\n\rthis room is unbelievable. The walls shimmer infront of you from the heat. \r\r\r\r\n\r",
            "Bits": [
                "INDOORS",
                "NOTELEPORT",
                "NORELOCATE",
                "NOQUIT"
            ],
            "Sector": "INSIDE",
            "Exits": [
                {
                    "Direction": "North",
                    "Description": "",
                    "Keywords": [],
                    "DoorFlags": null,
                    "KeyID": -1,
                    "Destination": 25115
                },
                {
                    "Direction": "South",
                    "Description": "",
                    "Keywords": [],
                    "DoorFlags": null,
                    "KeyID": -1,
                    "Destination": 25105
                }
            ],
            "ExtraDescs": null
        },
        {
            "ID": 25110,
            "Zone": 251,
            "Name": "Aboard the Chaos ship.",
            "Description": "Flashing yellow lights line this corridor accompanied by loud sirens. Bulkheads\r\r\r\r\n\rcan be seen above you scared and seared as if a huge battle took place here.\r\r\r\r\n\rSteel grates line the floor, some like as if they have been eaten through by\r\r\r\r\n\racid. The air in this room is so thin you can hardly breathe. \r\r\r\r\n\r",
            "Bits": [
                "INDOORS",
                "NOTELEPORT",
                "NORELOCATE",
                "NOQUIT"
            ],
            "Sector": "INSIDE",
            "Exits": [
                {
                    "Direction": "Northeast",
                    "Description": "",
                    "Keywords": [],
                    "DoorFlags": null,
                    "KeyID": -1,
                    "Destination": 25116
                },
                {
                    "Direction": "Southwest",
                    "Description": "",
                    "Keywords": [],
                    "DoorFlags": null,
                    "KeyID": -1,
                    "Destination": 25106
                }
            ],
            "ExtraDescs": null
        },
        {
            "ID": 25111,
            "Zone": 251,
            "Name": "Aboard the Chaos ship.",
            "Description": "Flashing yellow lights line this corridor accompanied by loud sirens. Bulkheads\r\r\r\r\n\rcan be seen above you scared and seared as if a huge battle took place here.\r\r\r\r\n\rThe heat in this room is unbelievable. The walls shimmer infront of you from\r\r\r\r\n\rthe heat. Steel grates line the floor, some like as if they have been eaten\r\r\r\r\n\rthrough by acid. \r\r\r\r\n\r",
            "Bits": [
                "INDOORS",
                "NOTELEPORT",
                "NORELOCATE",
                "NOQUIT"
            ],
            "Sector": "INSIDE",
            "Exits": [
                {
                    "Direction": "East",
                    "Description": "",
                    "Keywords": [],
                    "DoorFlags": null,
                    "KeyID": -1,
                    "Destination": 25112
                }
            ],
            "ExtraDescs": null
        },
        {
            "ID": 25112,
            "Zone": 251,
            "Name": "Aboard the Chaos ship.",
            "Description": "Flashing yellow lights line this corridor accompanied by loud sirens. Busted\r\r\r\r\n\rhoses and pipes spray steam and smoke into the room. Bodies of Imperial space\r\r\r\r\n\rmarines lay strewn across the floor. The air in this room is so thin you can\r\r\r\r\n\rhardly breathe. \r\r\r\r\n\r",
            "Bits": [
                "INDOORS",
                "NOTELEPORT",
                "NORELOCATE",
                "NOQUIT"
            ],
            "Sector": "INSIDE",
            "Exits": [
                {
                    "Direction": "North",
                    "Description": "",
                    "Keywords": [],
                    "DoorFlags": null,
                    "KeyID": -1,
                    "Destination": 25118
                },
                {
                    "Direction": "South",
                    "Description": "",
                    "Keywords": [],
                    "DoorFlags": null,
                    "KeyID": -1,
                    "Destination": 25107
                },
                {
                    "Direction": "West",
                    "Description": "",
                    "Keywords": [],
                    "DoorFlags": null,
                    "KeyID": -1,
                    "Destination": 25111
                }
            ],
            "ExtraDescs": null
        },
        {
            "ID": 25113,
            "Zone": 251,
            "Name": "Aboard the Chaos ship.",
            "Description": "\r",
            "Bits": [
                "DEATH",
                "INDOORS",
                "NOTELEPORT",
                "NORELOCATE",
                "NOQUIT",
                "NOFLEE"
            ],
            "Sector": "INSIDE",
            "Exits": [
                {
                    "Direction": "East",
                    "Description": "",
                    "Keywords": [],
                    "DoorFlags": null,
                    "KeyID": -1,
                    "Destination": 25114
                }
            ],
            "ExtraDescs": null
        },
        {
            "ID": 25114,
            "Zone": 251,
            "Name": "Aboard the Chaos ship.",
            "Description": "Flashing yellow lights line this corridor accompanied by loud sirens. Bulkheads\r\r\r\r\n\rcan be seen above you scared and seared as if a huge battle took place here.\r\r\r\r\n\rBodies of Imperial space marines lay strewn across the floor. The air in this\r\r\r\r\n\rroom is so thin you can hardly breathe. \r\r\r\r\n\r",
            "Bits": [
                "INDOORS",
                "NOTELEPORT",
                "NORELOCATE",
                "NOQUIT"
            ],
            "Sector": "INSIDE",
            "Exits": [
                {
                    "Direction": "North",
                    "Description": "",
                    "Keywords": [],
                    "DoorFlags": null,
                    "KeyID": -1,
                    "Destination": 25119
                },
                {
                    "Direction": "South",
                    "Description": "",
                    "Keywords": [],
                    "DoorFlags": null,
                    "KeyID": -1,
                    "Destination": 25108
                },
                {
                    "Direction": "West",
                    "Description": "",
                    "Keywords": [],
                    "DoorFlags": null,
                    "KeyID": -1,
                    "Destination": 25113
                }
            ],
            "ExtraDescs": null
        },
        {
            "ID": 25115,
            "Zone": 251,
            "Name": "Aboard the Chaos ship.",
            "Description": "Power must be shut off from this section of the ship because there are no light\r\r\r\r\n\rsources in this room. Busted hoses and pipes spray steam and smoke into the\r\r\r\r\n\rroom. The air here smells like sulfur and your eyes can not stop from\r\r\r\r\n\rwatering. Soot covers the floor with foot prints going into and out of the\r\r\r\r\n\rroom. \r\r\r\r\n\r",
            "Bits": [
                "INDOORS",
                "NOTELEPORT",
                "NORELOCATE",
                "NOQUIT"
            ],
            "Sector": "INSIDE",
            "Exits": [
                {
                    "Direction": "South",
                    "Description": "",
                    "Keywords": [],
                    "DoorFlags": null,
                    "KeyID": -1,
                    "Destination": 25109
                },
                {
                    "Direction": "Northeast",
                    "Description": "",
                    "Keywords": [],
                    "DoorFlags": null,
                    "KeyID": -1,
                    "Destination": 25120
                }
            ],
            "ExtraDescs": null
        },
        {
            "ID": 25116,
            "Zone": 251,
            "Name": "Aboard the Chaos ship.",
            "Description": "Flashing yellow lights line this corridor accompanied by loud sirens. Busted\r\r\r\r\n\rhoses and pipes spray steam and smoke into the room. Soot covers the floor\r\r\r\r\n\rwith foot prints going into and out of the room. The air in this room is so\r\r\r\r\n\rthin you can hardly breathe. \r\r\r\r\n\r",
            "Bits": [
                "INDOORS",
                "NOTELEPORT",
                "NORELOCATE",
                "NOQUIT"
            ],
            "Sector": "INSIDE",
            "Exits": [
                {
                    "Direction": "North",
                    "Description": "",
                    "Keywords": [],
                    "DoorFlags": null,
                    "KeyID": -1,
                    "Destination": 25121
                },
                {
                    "Direction": "East",
                    "Description": "",
                    "Keywords": [],
                    "DoorFlags": null,
                    "KeyID": -1,
                    "Destination": 25117
                },
                {
                    "Direction": "Southwest",
                    "Description": "",
                    "Keywords": [],
                    "DoorFlags": null,
                    "KeyID": -1,
                    "Destination": 25110
                }
            ],
            "ExtraDescs": null
        },
        {
            "ID": 25117,
            "Zone": 251,
            "Name": "Aboard the Chaos ship.",
            "Description": "Flashing yellow lights line this corridor accompanied by loud sirens. Busted\r\r\r\r\n\rhoses and pipes spray steam and smoke into the room. Stagnate air assualts\r\r\r\r\n\ryour senses as you step into the room. Bodies of Imperial space marines lay\r\r\r\r\n\rstrewn across the floor. \r\r\r\r\n\r",
            "Bits": [
                "INDOORS",
                "NOTELEPORT",
                "NORELOCATE",
                "NOQUIT"
            ],
            "Sector": "INSIDE",
            "Exits": [
                {
                    "Direction": "North",
                    "Description": "",
                    "Keywords": [],
                    "DoorFlags": null,
                    "KeyID": -1,
                    "Destination": 25122
                },
                {
                    "Direction": "West",
                    "Description": "",
                    "Keywords": [],
                    "DoorFlags": null,
                    "KeyID": -1,
                    "Destination": 25116
                }
            ],
            "ExtraDescs": null
        },
        {
            "ID": 25118,
            "Zone": 251,
            "Name": "Aboard the Chaos ship.",
            "Description": "Power must be shut off from this section of the ship because there are no light\r\r\r\r\n\rsources in this room. Busted hoses and pipes spray steam and smoke into the\r\r\r\r\n\rroom. The air here smells like sulfur and your eyes can not stop from\r\r\r\r\n\rwatering. Soot covers the floor with foot prints going into and out of the\r\r\r\r\n\rroom. \r\r\r\r\n\r",
            "Bits": [
                "INDOORS",
                "NOTELEPORT",
                "NORELOCATE",
                "NOQUIT"
            ],
            "Sector": "INSIDE",
            "Exits": [
                {
                    "Direction": "North",
                    "Description": "",
                    "Keywords": [],
                    "DoorFlags": null,
                    "KeyID": -1,
                    "Destination": 25123
                },
                {
                    "Direction": "South",
                    "Description": "",
                    "Keywords": [],
                    "DoorFlags": null,
                    "KeyID": -1,
                    "Destination": 25112
                }
            ],
            "ExtraDescs": null
        },
        {
            "ID": 25119,
            "Zone": 251,
            "Name": "Aboard the Chaos ship.",
            "Description": "Power must be shut off from this section of the ship because there are no light\r\r\r\r\n\rsources in this room. Green slime drips from the walls eating it's way through\r\r\r\r\n\rthe floor as it hits. Bodies of Imperial space marines lay strewn across the\r\r\r\r\n\rfloor. Cold air blasts your face as it streams out of a busted pipe. \r\r\r\r\n\r",
            "Bits": [
                "INDOORS",
                "NOTELEPORT",
                "NORELOCATE",
                "NOQUIT"
            ],
            "Sector": "INSIDE",
            "Exits": [
                {
                    "Direction": "South",
                    "Description": "",
                    "Keywords": [],
                    "DoorFlags": null,
                    "KeyID": -1,
                    "Destination": 25114
                },
                {
                    "Direction": "Northeast",
                    "Description": "",
                    "Keywords": [],
                    "DoorFlags": null,
                    "KeyID": -1,
                    "Destination": 25124
                }
            ],
            "ExtraDescs": null
        },
        {
            "ID": 25120,
            "Zone": 251,
            "Name": "Aboard the Chaos ship.",
            "Description": "Steel grates line the floor, some like as if they have been eaten through by\r\r\r\r\n\racid. The heat in this room is unbelievable. The walls shimmer infront of you\r\r\r\r\n\rfrom the heat. Busted hoses and pipes spray steam and smoke into the room.\r\r\r\r\n\rPower must be shut off from this section of the ship because there are no\r\r\r\r\n\rlight sources in this room. \r\r\r\r\n\r",
            "Bits": [
                "INDOORS",
                "NOTELEPORT",
                "NORELOCATE",
                "NOQUIT"
            ],
            "Sector": "INSIDE",
            "Exits": [
                {
                    "Direction": "North",
                    "Description": "",
                    "Keywords": [],
                    "DoorFlags": null,
                    "KeyID": -1,
                    "Destination": 25125
                },
                {
                    "Direction": "Southwest",
                    "Description": "",
                    "Keywords": [],
                    "DoorFlags": null,
                    "KeyID": -1,
                    "Destination": 25115
                }
            ],
            "ExtraDescs": null
        },
        {
            "ID": 25121,
            "Zone": 251,
            "Name": "Aboard the Chaos ship.",
            "Description": "Power must be shut off from this section of the ship because there are no light\r\r\r\r\n\rsources in this room. Demonic faces and pagan carvings can be seen on all the\r\r\r\r\n\rwalls in this room. Soot covers the floor with foot prints going into and out\r\r\r\r\n\rof the room. The heat in this room is unbelievable. The walls shimmer infront\r\r\r\r\n\rof you from the heat. \r\r\r\r\n\r",
            "Bits": [
                "INDOORS",
                "NOTELEPORT",
                "NORELOCATE",
                "NOQUIT"
            ],
            "Sector": "INSIDE",
            "Exits": [
                {
                    "Direction": "East",
                    "Description": "",
                    "Keywords": [],
                    "DoorFlags": null,
                    "KeyID": -1,
                    "Destination": 25122
                },
                {
                    "Direction": "South",
                    "Description": "",
                    "Keywords": [],
                    "DoorFlags": null,
                    "KeyID": -1,
                    "Destination": 25116
                },
                {
                    "Direction": "Northeast",
                    "Description": "",
                    "Keywords": [],
                    "DoorFlags": null,
                    "KeyID": -1,
                    "Destination": 25126
                }
            ],
            "ExtraDescs": null
        },
        {
            "ID": 25122,
            "Zone": 251,
            "Name": "Aboard the Chaos ship.",
            "Description": "Power must be shut off from this section of the ship because there are no light\r\r\r\r\n\rsources in this room. Demonic faces and pagan carvings can be seen on all the\r\r\r\r\n\rwalls in this room. The heat in this room is unbelievable. The walls shimmer\r\r\r\r\n\rinfront of you from the heat. Steel grates line the floor, some like as if\r\r\r\r\n\rthey have been eaten through by acid. \r\r\r\r\n\r",
            "Bits": [
                "INDOORS",
                "NOTELEPORT",
                "NORELOCATE",
                "NOQUIT"
            ],
            "Sector": "INSIDE",
            "Exits": [
                {
                    "Direction": "North",
                    "Description": "",
                    "Keywords": [],
                    "DoorFlags": null,
                    "KeyID": -1,
                    "Destination": 25126
                },
                {
                    "Direction": "South",
                    "Description": "",
                    "Keywords": [],
                    "DoorFlags": null,
                    "KeyID": -1,
                    "Destination": 25117
                },
                {
                    "Direction": "West",
                    "Description": "",
                    "Keywords": [],
                    "DoorFlags": null,
                    "KeyID": -1,
                    "Destination": 25122
                }
            ],
            "ExtraDescs": null
        },
        {
            "ID": 25123,
            "Zone": 251,
            "Name": "Aboard the Chaos ship.",
            "Description": "Power must be shut off from this section of the ship because there are no light\r\r\r\r\n\rsources in this room. Steel grates line the floor, some like as if they have\r\r\r\r\n\rbeen eaten through by acid. The heat in this room is unbelievable. The walls\r\r\r\r\n\rshimmer infront of you from the heat. Demonic faces and pagan carvings can be\r\r\r\r\n\rseen on all the walls in this room. \r\r\r\r\n\r",
            "Bits": [
                "INDOORS",
                "NOTELEPORT",
                "NORELOCATE",
                "NOQUIT"
            ],
            "Sector": "INSIDE",
            "Exits": [
                {
                    "Direction": "North",
                    "Description": "",
                    "Keywords": [],
                    "DoorFlags": null,
                    "KeyID": -1,
                    "Destination": 25128
                },
                {
                    "Direction": "South",
                    "Description": "",
                    "Keywords": [],
                    "DoorFlags": null,
                    "KeyID": -1,
                    "Destination": 25118
                }
            ],
            "ExtraDescs": null
        },
        {
            "ID": 25124,
            "Zone": 251,
            "Name": "Aboard the Chaos ship.",
            "Description": "Power must be shut off from this section of the ship because there are no light\r\r\r\r\n\rsources in this room. Soot covers the floor with foot prints going into and\r\r\r\r\n\rout of the room. Busted hoses and pipes spray steam and smoke into the room.\r\r\r\r\n\rCold air blasts your face as it streams out of a busted pipe. \r\r\r\r\n\r",
            "Bits": [
                "INDOORS",
                "NOTELEPORT",
                "NORELOCATE",
                "NOQUIT"
            ],
            "Sector": "INSIDE",
            "Exits": [
                {
                    "Direction": "Northwest",
                    "Description": "",
                    "Keywords": [],
                    "DoorFlags": null,
                    "KeyID": -1,
                    "Destination": 25129
                },
                {
                    "Direction": "Southwest",
                    "Description": "",
                    "Keywords": [],
                    "DoorFlags": null,
                    "KeyID": -1,
                    "Destination": 25119
                }
            ],
            "ExtraDescs": null
        },
        {
            "ID": 25125,
            "Zone": 251,
            "Name": "Aboard the Chaos ship.",
            "Description": "Power must be shut off from this section of the ship because there are no light\r\r\r\r\n\rsources in this room. Demonic faces and pagan carvings can be seen on all the\r\r\r\r\n\rwalls in this room. The air in this room is so thin you can hardly breathe.\r\r\r\r\n\rBodies of Imperial space marines lay strewn across the floor. \r\r\r\r\n\r",
            "Bits": [
                "INDOORS",
                "NOTELEPORT",
                "NORELOCATE",
                "NOQUIT"
            ],
            "Sector": "INSIDE",
            "Exits": [
                {
                    "Direction": "North",
                    "Description": "",
                    "Keywords": [],
                    "DoorFlags": null,
                    "KeyID": -1,
                    "Destination": 25130
                },
                {
                    "Direction": "South",
                    "Description": "",
                    "Keywords": [],
                    "DoorFlags": null,
                    "KeyID": -1,
                    "Destination": 25120
                }
            ],
            "ExtraDescs": null
        },
        {
            "ID": 25126,
            "Zone": 251,
            "Name": "Aboard the Chaos ship.",
            "Description": "Power must be shut off from this section of the ship because there are no light\r\r\r\r\n\rsources in this room. Soot covers the floor with foot prints going into and\r\r\r\r\n\rout of the room. Cold air blasts your face as it streams out of a busted pipe.\r\r\r\r\n\rDemonic faces and pagan carvings can be seen on all the walls in this room. \r\r\r\r\n\r",
            "Bits": [
                "INDOORS",
                "NOTELEPORT",
                "NORELOCATE",
                "NOQUIT"
            ],
            "Sector": "INSIDE",
            "Exits": [
                {
                    "Direction": "South",
                    "Description": "",
                    "Keywords": [],
                    "DoorFlags": null,
                    "KeyID": -1,
                    "Destination": 25122
                },
                {
                    "Direction": "Northwest",
                    "Description": "",
                    "Keywords": [],
                    "DoorFlags": null,
                    "KeyID": -1,
                    "Destination": 25131
                },
                {
                    "Direction": "Southwest",
                    "Description": "",
                    "Keywords": [],
                    "DoorFlags": null,
                    "KeyID": -1,
                    "Destination": 25121
                }
            ],
            "ExtraDescs": null
        },
        {
            "ID": 25127,
            "Zone": 251,
            "Name": "Aboard the Chaos ship.",
            "Description": "Soot covers the floor with foot prints going into and out of the room. Stagnate\r\r\r\r\n\rair assualts your senses as you step into the room. Yellow caution stripes can\r\r\r\r\n\rbe seen on the walls with hoses and tubes. Power must be shut off from this\r\r\r\r\n\rsection of the ship because there are no light sources in this room. \r\r\r\r\n\r",
            "Bits": [
                "INDOORS",
                "NOTELEPORT",
                "NORELOCATE",
                "NOQUIT"
            ],
            "Sector": "INSIDE",
            "Exits": [
                {
                    "Direction": "North",
                    "Description": "",
                    "Keywords": [],
                    "DoorFlags": null,
                    "KeyID": -1,
                    "Destination": 25133
                },
                {
                    "Direction": "East",
                    "Description": "",
                    "Keywords": [],
                    "DoorFlags": null,
                    "KeyID": -1,
                    "Destination": 25128
                }
            ],
            "ExtraDescs": null
        },
        {
            "ID": 25128,
            "Zone": 251,
            "Name": "Aboard the Chaos ship.",
            "Description": "Busted hoses and pipes spray steam and smoke into the room. Stagnate air\r\r\r\r\n\rassualts your senses as you step into the room. Bodies of Imperial space\r\r\r\r\n\rmarines lay strewn across the floor. Power must be shut off from this section\r\r\r\r\n\rof the ship because there are no light sources in this room. \r\r\r\r\n\r",
            "Bits": [
                "INDOORS",
                "NOTELEPORT",
                "NORELOCATE",
                "NOQUIT"
            ],
            "Sector": "INSIDE",
            "Exits": [
                {
                    "Direction": "South",
                    "Description": "",
                    "Keywords": [],
                    "DoorFlags": null,
                    "KeyID": -1,
                    "Destination": 25123
                },
                {
                    "Direction": "West",
                    "Description": "",
                    "Keywords": [],
                    "DoorFlags": null,
                    "KeyID": -1,
                    "Destination": 25127
                }
            ],
            "ExtraDescs": null
        },
        {
            "ID": 25129,
            "Zone": 251,
            "Name": "Aboard the Chaos ship.",
            "Description": "Power must be shut off from this section of the ship because there are no light\r\r\r\r\n\rsources in this room. Busted hoses and pipes spray steam and smoke into the\r\r\r\r\n\rroom. Stagnate air assualts your senses as you step into the room. Bodies of\r\r\r\r\n\rImperial space marines lay strewn across the floor. \r\r\r\r\n\r",
            "Bits": [
                "INDOORS",
                "NOTELEPORT",
                "NORELOCATE",
                "NOQUIT"
            ],
            "Sector": "INSIDE",
            "Exits": [
                {
                    "Direction": "North",
                    "Description": "",
                    "Keywords": [],
                    "DoorFlags": null,
                    "KeyID": -1,
                    "Destination": 25135
                },
                {
                    "Direction": "Southwest",
                    "Description": "",
                    "Keywords": [],
                    "DoorFlags": null,
                    "KeyID": -1,
                    "Destination": 25124
                }
            ],
            "ExtraDescs": null
        },
        {
            "ID": 25130,
            "Zone": 251,
            "Name": "Aboard the Chaos ship.",
            "Description": "Power must be shut off from this section of the ship because there are no light\r\r\r\r\n\rsources in this room. Busted hoses and pipes spray steam and smoke into the\r\r\r\r\n\rroom. Cold air blasts your face as it streams out of a busted pipe. Small port\r\r\r\r\n\rholes let you look out into the high atomsphere of Macragge. \r\r\r\r\n\r",
            "Bits": [
                "INDOORS",
                "NOTELEPORT",
                "NORELOCATE",
                "NOQUIT"
            ],
            "Sector": "INSIDE",
            "Exits": [
                {
                    "Direction": "North",
                    "Description": "",
                    "Keywords": [],
                    "DoorFlags": null,
                    "KeyID": -1,
                    "Destination": 25137
                },
                {
                    "Direction": "South",
                    "Description": "",
                    "Keywords": [],
                    "DoorFlags": null,
                    "KeyID": -1,
                    "Destination": 25125
                }
            ],
            "ExtraDescs": null
        },
        {
            "ID": 25131,
            "Zone": 251,
            "Name": "Aboard the Chaos ship.",
            "Description": "Power must be shut off from this section of the ship because there are no light\r\r\r\r\n\rsources in this room. Busted hoses and pipes spray steam and smoke into the\r\r\r\r\n\rroom. The air here smells like sulfur and your eyes can not stop from\r\r\r\r\n\rwatering. Steel grates line the floor, some like as if they have been eaten\r\r\r\r\n\rthrough by acid. \r\r\r\r\n\r",
            "Bits": [
                "INDOORS",
                "NOTELEPORT",
                "NORELOCATE",
                "NOQUIT"
            ],
            "Sector": "INSIDE",
            "Exits": [
                {
                    "Direction": "Northeast",
                    "Description": "",
                    "Keywords": [],
                    "DoorFlags": null,
                    "KeyID": -1,
                    "Destination": 25138
                },
                {
                    "Direction": "Southeast",
                    "Description": "",
                    "Keywords": [],
                    "DoorFlags": null,
                    "KeyID": -1,
                    "Destination": 25126
                }
            ],
            "ExtraDescs": null
        },
        {
            "ID": 25132,
            "Zone": 251,
            "Name": "Aboard the Chaos ship.",
            "Description": "Power must be shut off from this section of the ship because there are no light\r\r\r\r\n\rsources in this room. Soot covers the floor with foot prints going into and\r\r\r\r\n\rout of the room. The air here smells like sulfur and your eyes can not stop\r\r\r\r\n\rfrom watering. Busted hoses and pipes spray steam and smoke into the room. \r\r\r\r\n\r",
            "Bits": [
                "INDOORS",
                "NOTELEPORT",
                "NORELOCATE",
                "NOQUIT"
            ],
            "Sector": "INSIDE",
            "Exits": [
                {
                    "Direction": "East",
                    "Description": "",
                    "Keywords": [],
                    "DoorFlags": null,
                    "KeyID": -1,
                    "Destination": 25134
                }
            ],
            "ExtraDescs": null
        },
        {
            "ID": 25133,
            "Zone": 251,
            "Name": "Aboard the Chaos ship.",
            "Description": "Power must be shut off from this section of the ship because there are no light\r\r\r\r\n\rsources in this room. Busted hoses and pipes spray steam and smoke into the\r\r\r\r\n\rroom. The heat in this room is unbelievable. The walls shimmer infront of you\r\r\r\r\n\rfrom the heat. Steel grates line the floor, some like as if they have been\r\r\r\r\n\reaten through by acid. \r\r\r\r\n\r",
            "Bits": [
                "INDOORS",
                "NOTELEPORT",
                "NORELOCATE",
                "NOQUIT"
            ],
            "Sector": "INSIDE",
            "Exits": [
                {
                    "Direction": "North",
                    "Description": "",
                    "Keywords": [],
                    "DoorFlags": null,
                    "KeyID": -1,
                    "Destination": 25139
                },
                {
                    "Direction": "South",
                    "Description": "",
                    "Keywords": [],
                    "DoorFlags": null,
                    "KeyID": -1,
                    "Destination": 25127
                },
                {
                    "Direction": "West",
                    "Description": "",
                    "Keywords": [],
                    "DoorFlags": null,
                    "KeyID": -1,
                    "Destination": 25132
                }
            ],
            "ExtraDescs": null
        },
        {
            "ID": 25134,
            "Zone": 251,
            "Name": "Aboard the Chaos ship.",
            "Description": "Power must be shut off from this section of the ship because there are no light\r\r\r\r\n\rsources in this room. Busted hoses and pipes spray steam and smoke into the\r\r\r\r\n\rroom. Stagnate air assualts your senses as you step into the room. Bodies of\r\r\r\r\n\rImperial space marines lay strewn across the floor. \r\r\r\r\n\r",
            "Bits": [
                "INDOORS",
                "NOTELEPORT",
                "NORELOCATE",
                "NOQUIT"
            ],
            "Sector": "INSIDE",
            "Exits": [
                {
                    "Direction": "North",
                    "Description": "",
                    "Keywords": [],
                    "DoorFlags": null,
                    "KeyID": -1,
                    "Destination": 25140
                },
                {
                    "Direction": "East",
                    "Description": "",
                    "Keywords": [],
                    "DoorFlags": null,
                    "KeyID": -1,
                    "Destination": 25135
                }
            ],
            "ExtraDescs": null
        },
        {
            "ID": 25135,
            "Zone": 251,
            "Name": "Aboard the Chaos ship.",
            "Description": "Power must be shut off from this section of the ship because there are no light\r\r\r\r\n\rsources in this room. Busted hoses and pipes spray steam and smoke into the\r\r\r\r\n\rroom. Steel grates line the floor, some like as if they have been eaten\r\r\r\r\n\rthrough by acid. Cold air blasts your face as it streams out of a busted pipe.\r\r\r\r\n\r",
            "Bits": [
                "INDOORS",
                "NOTELEPORT",
                "NORELOCATE",
                "NOQUIT"
            ],
            "Sector": "INSIDE",
            "Exits": [
                {
                    "Direction": "South",
                    "Description": "",
                    "Keywords": [],
                    "DoorFlags": null,
                    "KeyID": -1,
                    "Destination": 25129
                },
                {
                    "Direction": "West",
                    "Description": "",
                    "Keywords": [],
                    "DoorFlags": null,
                    "KeyID": -1,
                    "Destination": 25134
                }
            ],
            "ExtraDescs": null
        },
        {
            "ID": 25136,
            "Zone": 251,
            "Name": "Aboard the Chaos ship.",
            "Description": "Power must be shut off from this section of the ship because there are no light\r\r\r\r\n\rsources in this room. Cold air blasts your face as it streams out of a busted\r\r\r\r\n\rpipe. Bulkheads can be seen above you scared and seared as if a huge battle\r\r\r\r\n\rtook place here. Soot covers the floor with foot prints going into and out of\r\r\r\r\n\rthe room. \r\r\r\r\n\r",
            "Bits": [
                "INDOORS",
                "NOTELEPORT",
                "NORELOCATE",
                "NOQUIT"
            ],
            "Sector": "INSIDE",
            "Exits": [
                {
                    "Direction": "East",
                    "Description": "",
                    "Keywords": [],
                    "DoorFlags": null,
                    "KeyID": -1,
                    "Destination": 25137
                }
            ],
            "ExtraDescs": null
        },
        {
            "ID": 25137,
            "Zone": 251,
            "Name": "Aboard the Chaos ship.",
            "Description": "Busted hoses and pipes spray steam and smoke into the room. Stagnate air\r\r\r\r\n\rassualts your senses as you step into the room. Power must be shut off from\r\r\r\r\n\rthis section of the ship because there are no light sources in this room.\r\r\r\r\n\rSteel grates line the floor, some like as if they have been eaten through by\r\r\r\r\n\racid. \r\r\r\r\n\r",
            "Bits": [
                "INDOORS",
                "NOTELEPORT",
                "NORELOCATE",
                "NOQUIT"
            ],
            "Sector": "INSIDE",
            "Exits": [
                {
                    "Direction": "North",
                    "Description": "",
                    "Keywords": [],
                    "DoorFlags": null,
                    "KeyID": -1,
                    "Destination": 25141
                },
                {
                    "Direction": "South",
                    "Description": "",
                    "Keywords": [],
                    "DoorFlags": null,
                    "KeyID": -1,
                    "Destination": 25130
                },
                {
                    "Direction": "West",
                    "Description": "",
                    "Keywords": [],
                    "DoorFlags": null,
                    "KeyID": -1,
                    "Destination": 25136
                }
            ],
            "ExtraDescs": null
        },
        {
            "ID": 25138,
            "Zone": 251,
            "Name": "Aboard the Chaos ship.",
            "Description": "Power must be shut off from this section of the ship because there are no light\r\r\r\r\n\rsources in this room. Steel grates line the floor, some like as if they have\r\r\r\r\n\rbeen eaten through by acid. Cold air blasts your face as it streams out of a\r\r\r\r\n\rbusted pipe. Yellow caution stripes can be seen on the walls with hoses and\r\r\r\r\n\rtubes. \r\r\r\r\n\r",
            "Bits": [
                "INDOORS",
                "NOTELEPORT",
                "NORELOCATE",
                "NOQUIT"
            ],
            "Sector": "INSIDE",
            "Exits": [
                {
                    "Direction": "Northeast",
                    "Description": "",
                    "Keywords": [],
                    "DoorFlags": null,
                    "KeyID": -1,
                    "Destination": 25143
                }
            ],
            "ExtraDescs": null
        },
        {
            "ID": 25139,
            "Zone": 251,
            "Name": "Aboard the Chaos ship.",
            "Description": "Two large overhead lamps provide the light for this room. Steel grates line the\r\r\r\r\n\rfloor, some like as if they have been eaten through by acid. Cold air blasts\r\r\r\r\n\ryour face as it streams out of a busted pipe. Busted hoses and pipes spray\r\r\r\r\n\rsteam and smoke into the room. \r\r\r\r\n\r",
            "Bits": [
                "INDOORS",
                "NOTELEPORT",
                "NORELOCATE",
                "NOQUIT"
            ],
            "Sector": "INSIDE",
            "Exits": [
                {
                    "Direction": "South",
                    "Description": "",
                    "Keywords": [],
                    "DoorFlags": null,
                    "KeyID": -1,
                    "Destination": 25133
                },
                {
                    "Direction": "Northeast",
                    "Description": "",
                    "Keywords": [],
                    "DoorFlags": null,
                    "KeyID": -1,
                    "Destination": 25144
                }
            ],
            "ExtraDescs": null
        },
        {
            "ID": 25140,
            "Zone": 251,
            "Name": "Aboard the Chaos ship.",
            "Description": "Two large overhead lamps provide the light for this room. Steel grates line the\r\r\r\r\n\rfloor, some like as if they have been eaten through by acid. Busted hoses and\r\r\r\r\n\rpipes spray steam and smoke into the room. Cold air blasts your face as it\r\r\r\r\n\rstreams out of a busted pipe. \r\r\r\r\n\r",
            "Bits": [
                "INDOORS",
                "NOTELEPORT",
                "NORELOCATE",
                "NOQUIT"
            ],
            "Sector": "INSIDE",
            "Exits": [
                {
                    "Direction": "South",
                    "Description": "",
                    "Keywords": [],
                    "DoorFlags": null,
                    "KeyID": -1,
                    "Destination": 25134
                },
                {
                    "Direction": "Northwest",
                    "Description": "",
                    "Keywords": [],
                    "DoorFlags": null,
                    "KeyID": -1,
                    "Destination": 25145
                }
            ],
            "ExtraDescs": null
        },
        {
            "ID": 25141,
            "Zone": 251,
            "Name": "Aboard the Chaos ship.",
            "Description": "Soot covers the floor with foot prints going into and out of the room. Cold air\r\r\r\r\n\rblasts your face as it streams out of a busted pipe. Demonic faces and pagan\r\r\r\r\n\rcarvings can be seen on all the walls in this room. Two large overhead lamps\r\r\r\r\n\rprovide the light for this room. \r\r\r\r\n\r",
            "Bits": [
                "INDOORS",
                "NOTELEPORT",
                "NORELOCATE",
                "NOQUIT"
            ],
            "Sector": "INSIDE",
            "Exits": [
                {
                    "Direction": "East",
                    "Description": "",
                    "Keywords": [],
                    "DoorFlags": null,
                    "KeyID": -1,
                    "Destination": 25142
                },
                {
                    "Direction": "South",
                    "Description": "",
                    "Keywords": [],
                    "DoorFlags": null,
                    "KeyID": -1,
                    "Destination": 25137
                }
            ],
            "ExtraDescs": null
        },
        {
            "ID": 25142,
            "Zone": 251,
            "Name": "Aboard the Chaos ship.",
            "Description": "Soot covers the floor with foot prints going into and out of the room. Stagnate\r\r\r\r\n\rair assualts your senses as you step into the room. Yellow caution stripes can\r\r\r\r\n\rbe seen on the walls with hoses and tubes. Two large overhead lamps provide\r\r\r\r\n\rthe light for this room. \r\r\r\r\n\r",
            "Bits": [
                "INDOORS",
                "NOTELEPORT",
                "NORELOCATE",
                "NOQUIT"
            ],
            "Sector": "INSIDE",
            "Exits": [
                {
                    "Direction": "West",
                    "Description": "",
                    "Keywords": [],
                    "DoorFlags": null,
                    "KeyID": -1,
                    "Destination": 25141
                },
                {
                    "Direction": "Northeast",
                    "Description": "",
                    "Keywords": [],
                    "DoorFlags": null,
                    "KeyID": -1,
                    "Destination": 25146
                }
            ],
            "ExtraDescs": null
        },
        {
            "ID": 25143,
            "Zone": 251,
            "Name": "Aboard the Chaos ship.",
            "Description": "Busted hoses and pipes spray steam and smoke into the room. Stagnate air\r\r\r\r\n\rassualts your senses as you step into the room. Bodies of Imperial space\r\r\r\r\n\rmarines lay strewn across the floor. Two large overhead lamps provide the\r\r\r\r\n\rlight for this room. \r\r\r\r\n\r",
            "Bits": [
                "INDOORS",
                "NOTELEPORT",
                "NORELOCATE",
                "NOQUIT"
            ],
            "Sector": "INSIDE",
            "Exits": [
                {
                    "Direction": "Northeast",
                    "Description": "",
                    "Keywords": [],
                    "DoorFlags": null,
                    "KeyID": -1,
                    "Destination": 25152
                },
                {
                    "Direction": "Southwest",
                    "Description": "",
                    "Keywords": [],
                    "DoorFlags": null,
                    "KeyID": -1,
                    "Destination": 25138
                }
            ],
            "ExtraDescs": null
        },
        {
            "ID": 25144,
            "Zone": 251,
            "Name": "Aboard the Chaos ship.",
            "Description": "Busted hoses and pipes spray steam and smoke into the room. Steel grates line\r\r\r\r\n\rthe floor, some like as if they have been eaten through by acid. The air in\r\r\r\r\n\rthis room is so thin you can hardly breathe. Two large overhead lamps provide\r\r\r\r\n\rthe light for this room. \r\r\r\r\n\r",
            "Bits": [
                "INDOORS",
                "NOTELEPORT",
                "NORELOCATE",
                "NOQUIT"
            ],
            "Sector": "INSIDE",
            "Exits": [
                {
                    "Direction": "North",
                    "Description": "",
                    "Keywords": [],
                    "DoorFlags": null,
                    "KeyID": -1,
                    "Destination": 25148
                },
                {
                    "Direction": "East",
                    "Description": "",
                    "Keywords": [],
                    "DoorFlags": null,
                    "KeyID": -1,
                    "Destination": 25145
                },
                {
                    "Direction": "Southwest",
                    "Description": "",
                    "Keywords": [],
                    "DoorFlags": null,
                    "KeyID": -1,
                    "Destination": 25139
                }
            ],
            "ExtraDescs": null
        },
        {
            "ID": 25145,
            "Zone": 251,
            "Name": "Aboard the Chaos ship.",
            "Description": "Two large overhead lamps provide the light for this room. Steel grates line the\r\r\r\r\n\rfloor, some like as if they have been eaten through by acid. The air in this\r\r\r\r\n\rroom is so thin you can hardly breathe. Busted hoses and pipes spray steam and\r\r\r\r\n\rsmoke into the room. \r\r\r\r\n\r",
            "Bits": [
                "INDOORS",
                "NOTELEPORT",
                "NORELOCATE",
                "NOQUIT"
            ],
            "Sector": "INSIDE",
            "Exits": [
                {
                    "Direction": "Southeast",
                    "Description": "",
                    "Keywords": [],
                    "DoorFlags": null,
                    "KeyID": -1,
                    "Destination": 25140
                }
            ],
            "ExtraDescs": null
        },
        {
            "ID": 25146,
            "Zone": 251,
            "Name": "Aboard the Chaos ship.",
            "Description": "Busted hoses and pipes spray steam and smoke into the room. Steel grates line\r\r\r\r\n\rthe floor, some like as if they have been eaten through by acid. The air in\r\r\r\r\n\rthis room is so thin you can hardly breathe. Two large overhead lamps provide\r\r\r\r\n\rthe light for this room. \r\r\r\r\n\r",
            "Bits": [
                "INDOORS",
                "NOTELEPORT",
                "NORELOCATE",
                "NOQUIT"
            ],
            "Sector": "INSIDE",
            "Exits": [
                {
                    "Direction": "North",
                    "Description": "",
                    "Keywords": [],
                    "DoorFlags": null,
                    "KeyID": -1,
                    "Destination": 25151
                },
                {
                    "Direction": "Southwest",
                    "Description": "",
                    "Keywords": [],
                    "DoorFlags": null,
                    "KeyID": -1,
                    "Destination": 25142
                }
            ],
            "ExtraDescs": null
        },
        {
            "ID": 25147,
            "Zone": 251,
            "Name": "Aboard the Chaos ship.",
            "Description": "Busted hoses and pipes spray steam and smoke into the room. The air in this\r\r\r\r\n\rroom is so thin you can hardly breathe. Bodies of Imperial space marines lay\r\r\r\r\n\rstrewn across the floor. Two large overhead lamps provide the light for this\r\r\r\r\n\rroom. \r\r\r\r\n\r",
            "Bits": [
                "INDOORS",
                "NOTELEPORT",
                "NORELOCATE",
                "NOQUIT"
            ],
            "Sector": "INSIDE",
            "Exits": [
                {
                    "Direction": "Northeast",
                    "Description": "",
                    "Keywords": [],
                    "DoorFlags": null,
                    "KeyID": -1,
                    "Destination": 25152
                },
                {
                    "Direction": "Southwest",
                    "Description": "",
                    "Keywords": [],
                    "DoorFlags": null,
                    "KeyID": -1,
                    "Destination": 25143
                }
            ],
            "ExtraDescs": null
        },
        {
            "ID": 25148,
            "Zone": 251,
            "Name": "Aboard the Chaos ship.",
            "Description": "Two large overhead lamps provide the light for this room. Steel grates line the\r\r\r\r\n\rfloor, some like as if they have been eaten through by acid. The air in this\r\r\r\r\n\rroom is so thin you can hardly breathe. Busted hoses and pipes spray steam and\r\r\r\r\n\rsmoke into the room. \r\r\r\r\n\r",
            "Bits": [
                "INDOORS",
                "NOTELEPORT",
                "NORELOCATE",
                "NOQUIT"
            ],
            "Sector": "INSIDE",
            "Exits": [
                {
                    "Direction": "North",
                    "Description": "This hatchway leads to...\r\r\r\r\n\r",
                    "Keywords": [
                        "Hatchway"
                    ],
                    "DoorFlags": [
                        "NORMAL"
                    ],
                    "KeyID": -1,
                    "Destination": 25153
                },
                {
                    "Direction": "South",
                    "Description": "",
                    "Keywords": [],
                    "DoorFlags": null,
                    "KeyID": -1,
                    "Destination": 25144
                }
            ],
            "ExtraDescs": null
        },
        {
            "ID": 25149,
            "Zone": 251,
            "Name": "Aboard the Chaos ship.",
            "Description": "Two large overhead lamps provide the light for this room. Demonic faces and\r\r\r\r\n\rpagan carvings can be seen on all the walls in this room. The air in this room\r\r\r\r\n\ris so thin you can hardly breathe. Small port holes let you look out into the\r\r\r\r\n\rhigh atomsphere of Macragge. \r\r\r\r\n\r",
            "Bits": [
                "INDOORS",
                "NOTELEPORT",
                "NORELOCATE",
                "NOQUIT"
            ],
            "Sector": "INSIDE",
            "Exits": [
                {
                    "Direction": "North",
                    "Description": "",
                    "Keywords": [],
                    "DoorFlags": null,
                    "KeyID": -1,
                    "Destination": 25155
                }
            ],
            "ExtraDescs": null
        },
        {
            "ID": 25150,
            "Zone": 251,
            "Name": "Aboard the Chaos ship.",
            "Description": "Steel grates line the floor, some like as if they have been eaten through by\r\r\r\r\n\racid. The air in this room is so thin you can hardly breathe. Yellow caution\r\r\r\r\n\rstripes can be seen on the walls with hoses and tubes. Two large overhead\r\r\r\r\n\rlamps provide the light for this room. \r\r\r\r\n\r",
            "Bits": [
                "INDOORS",
                "NOTELEPORT",
                "NORELOCATE",
                "NOQUIT"
            ],
            "Sector": "INSIDE",
            "Exits": [
                {
                    "Direction": "North",
                    "Description": "",
                    "Keywords": [],
                    "DoorFlags": null,
                    "KeyID": -1,
                    "Destination": 25156
                },
                {
                    "Direction": "East",
                    "Description": "",
                    "Keywords": [],
                    "DoorFlags": null,
                    "KeyID": -1,
                    "Destination": 25151
                }
            ],
            "ExtraDescs": null
        },
        {
            "ID": 25151,
            "Zone": 251,
            "Name": "Aboard the Chaos ship.",
            "Description": "Two large overhead lamps provide the light for this room. Steel grates line the\r\r\r\r\n\rfloor, some like as if they have been eaten through by acid. The heat in this\r\r\r\r\n\rroom is unbelievable. The walls shimmer infront of you from the heat. Green\r\r\r\r\n\rslime drips from the walls eating it's way through the floor as it hits. \r\r\r\r\n\r",
            "Bits": [
                "INDOORS",
                "NOTELEPORT",
                "NORELOCATE",
                "NOQUIT"
            ],
            "Sector": "INSIDE",
            "Exits": [
                {
                    "Direction": "South",
                    "Description": "",
                    "Keywords": [],
                    "DoorFlags": null,
                    "KeyID": -1,
                    "Destination": 25146
                },
                {
                    "Direction": "West",
                    "Description": "",
                    "Keywords": [],
                    "DoorFlags": null,
                    "KeyID": -1,
                    "Destination": 25150
                }
            ],
            "ExtraDescs": null
        },
        {
            "ID": 25152,
            "Zone": 251,
            "Name": "Aboard the Chaos ship.",
            "Description": "Two large overhead lamps provide the light for this room. Steel grates line the\r\r\r\r\n\rfloor, some like as if they have been eaten through by acid. Stagnate air\r\r\r\r\n\rassualts your senses as you step into the room. Yellow caution stripes can be\r\r\r\r\n\rseen on the walls with hoses and tubes. \r\r\r\r\n\r",
            "Bits": [
                "INDOORS",
                "NOTELEPORT",
                "NORELOCATE",
                "NOQUIT"
            ],
            "Sector": "INSIDE",
            "Exits": [
                {
                    "Direction": "Southwest",
                    "Description": "",
                    "Keywords": [],
                    "DoorFlags": null,
                    "KeyID": -1,
                    "Destination": 25147
                }
            ],
            "ExtraDescs": null
        },
        {
            "ID": 25153,
            "Zone": 251,
            "Name": "Aboard the Chaos ship.",
            "Description": "Busted hoses and pipes spray steam and smoke into the room. Stagnate air\r\r\r\r\n\rassualts your senses as you step into the room. Bodies of Imperial space\r\r\r\r\n\rmarines lay strewn across the floor. Two large overhead lamps provide the\r\r\r\r\n\rlight for this room. \r\r\r\r\n\r",
            "Bits": [
                "INDOORS",
                "NOTELEPORT",
                "NORELOCATE",
                "NOQUIT"
            ],
            "Sector": "INSIDE",
            "Exits": [
                {
                    "Direction": "South",
                    "Description": "",
                    "Keywords": [],
                    "DoorFlags": null,
                    "KeyID": -1,
                    "Destination": 25148
                }
            ],
            "ExtraDescs": null
        },
        {
            "ID": 25154,
            "Zone": 251,
            "Name": "Aboard the Chaos ship.",
            "Description": "Two large overhead lamps provide the light for this room. Steel grates line the\r\r\r\r\n\rfloor, some like as if they have been eaten through by acid. The heat in this\r\r\r\r\n\rroom is unbelievable. The walls shimmer infront of you from the heat. Yellow\r\r\r\r\n\rcaution stripes can be seen on the walls with hoses and tubes. \r\r\r\r\n\r",
            "Bits": [
                "INDOORS",
                "NOTELEPORT",
                "NORELOCATE",
                "NOQUIT"
            ],
            "Sector": "INSIDE",
            "Exits": [
                {
                    "Direction": "North",
                    "Description": "",
                    "Keywords": [],
                    "DoorFlags": null,
                    "KeyID": -1,
                    "Destination": 25158
                },
                {
                    "Direction": "East",
                    "Description": "",
                    "Keywords": [],
                    "DoorFlags": null,
                    "KeyID": -1,
                    "Destination": 25155
                }
            ],
            "ExtraDescs": null
        },
        {
            "ID": 25155,
            "Zone": 251,
            "Name": "Aboard the Chaos ship.",
            "Description": "Small flood lights pour light into this room leaving no trace of shadows.\r\r\r\r\n\rBusted hoses and pipes spray steam and smoke into the room. Stagnate air\r\r\r\r\n\rassualts your senses as you step into the room. Bodies of Imperial space\r\r\r\r\n\rmarines lay strewn across the floor. \r\r\r\r\n\r",
            "Bits": [
                "INDOORS",
                "NOTELEPORT",
                "NORELOCATE",
                "NOQUIT"
            ],
            "Sector": "INSIDE",
            "Exits": [
                {
                    "Direction": "East",
                    "Description": "",
                    "Keywords": [],
                    "DoorFlags": null,
                    "KeyID": -1,
                    "Destination": 25156
                },
                {
                    "Direction": "South",
                    "Description": "",
                    "Keywords": [],
                    "DoorFlags": null,
                    "KeyID": -1,
                    "Destination": 25149
                },
                {
                    "Direction": "West",
                    "Description": "",
                    "Keywords": [],
                    "DoorFlags": null,
                    "KeyID": -1,
                    "Destination": 25154
                }
            ],
            "ExtraDescs": null
        },
        {
            "ID": 25156,
            "Zone": 251,
            "Name": "Aboard the Chaos ship.",
            "Description": "Small flood lights pour light into this room leaving no trace of shadows. The\r\r\r\r\n\rair in this room is so thin you can hardly breathe. Bodies of Imperial space\r\r\r\r\n\rmarines lay strewn across the floor. Bulkheads can be seen above you scared\r\r\r\r\n\rand seared as if a huge battle took place here. \r\r\r\r\n\r",
            "Bits": [
                "INDOORS",
                "NOTELEPORT",
                "NORELOCATE",
                "NOQUIT"
            ],
            "Sector": "INSIDE",
            "Exits": [
                {
                    "Direction": "South",
                    "Description": "",
                    "Keywords": [],
                    "DoorFlags": null,
                    "KeyID": -1,
                    "Destination": 25150
                },
                {
                    "Direction": "West",
                    "Description": "",
                    "Keywords": [],
                    "DoorFlags": null,
                    "KeyID": -1,
                    "Destination": 25155
                }
            ],
            "ExtraDescs": null
        },
        {
            "ID": 25157,
            "Zone": 251,
            "Name": "Aboard the Chaos ship.",
            "Description": "Power must be shut off from this section of the ship because there are no light\r\r\r\r\n\rsources in this room. Steel grates line the floor, some like as if they have\r\r\r\r\n\rbeen eaten through by acid. The heat in this room is unbelievable. The walls\r\r\r\r\n\rshimmer infront of you from the heat. Demonic faces and pagan carvings can be\r\r\r\r\n\rseen on all the walls in this room. \r\r\r\r\n\r",
            "Bits": [
                "INDOORS",
                "NOTELEPORT",
                "NORELOCATE",
                "NOQUIT"
            ],
            "Sector": "INSIDE",
            "Exits": [
                {
                    "Direction": "North",
                    "Description": "",
                    "Keywords": [],
                    "DoorFlags": null,
                    "KeyID": -1,
                    "Destination": 25161
                },
                {
                    "Direction": "Southwest",
                    "Description": "",
                    "Keywords": [],
                    "DoorFlags": null,
                    "KeyID": -1,
                    "Destination": 25152
                }
            ],
            "ExtraDescs": null
        },
        {
            "ID": 25158,
            "Zone": 251,
            "Name": "Aboard the Chaos ship.",
            "Description": "Two large overhead lamps provide the light for this room. Busted hoses and\r\r\r\r\n\rpipes spray steam and smoke into the room. Steel grates line the floor, some\r\r\r\r\n\rlike as if they have been eaten through by acid. The air in this room is so\r\r\r\r\n\rthin you can hardly breathe. \r\r\r\r\n\r",
            "Bits": [
                "INDOORS",
                "NOTELEPORT",
                "NORELOCATE",
                "NOQUIT"
            ],
            "Sector": "INSIDE",
            "Exits": [
                {
                    "Direction": "East",
                    "Description": "",
                    "Keywords": [],
                    "DoorFlags": null,
                    "KeyID": -1,
                    "Destination": 25159
                },
                {
                    "Direction": "South",
                    "Description": "",
                    "Keywords": [],
                    "DoorFlags": null,
                    "KeyID": -1,
                    "Destination": 25154
                }
            ],
            "ExtraDescs": null
        },
        {
            "ID": 25159,
            "Zone": 251,
            "Name": "Aboard the Chaos ship.",
            "Description": "Power must be shut off from this section of the ship because there are no light\r\r\r\r\n\rsources in this room. Steel grates line the floor, some like as if they have\r\r\r\r\n\rbeen eaten through by acid. The air in this room is so thin you can hardly\r\r\r\r\n\rbreathe. Yellow caution stripes can be seen on the walls with hoses and tubes.\r\r\r\r\n\r",
            "Bits": [
                "INDOORS",
                "NOTELEPORT",
                "NORELOCATE",
                "NOQUIT"
            ],
            "Sector": "INSIDE",
            "Exits": [
                {
                    "Direction": "North",
                    "Description": "",
                    "Keywords": [],
                    "DoorFlags": null,
                    "KeyID": -1,
                    "Destination": 25162
                },
                {
                    "Direction": "West",
                    "Description": "",
                    "Keywords": [],
                    "DoorFlags": null,
                    "KeyID": -1,
                    "Destination": 25158
                }
            ],
            "ExtraDescs": null
        },
        {
            "ID": 25160,
            "Zone": 251,
            "Name": "Aboard the Chaos ship.",
            "Description": "Two large overhead lamps provide the light for this room. The air in this room\r\r\r\r\n\ris so thin you can hardly breathe. Small port holes let you look out into the\r\r\r\r\n\rhigh atomsphere of Macragge. Demonic faces and pagan carvings can be seen on\r\r\r\r\n\rall the walls in this room. \r\r\r\r\n\r",
            "Bits": [
                "INDOORS",
                "NOTELEPORT",
                "NORELOCATE",
                "NOQUIT"
            ],
            "Sector": "INSIDE",
            "Exits": [
                {
                    "Direction": "North",
                    "Description": "",
                    "Keywords": [],
                    "DoorFlags": null,
                    "KeyID": -1,
                    "Destination": 25163
                },
                {
                    "Direction": "East",
                    "Description": "",
                    "Keywords": [],
                    "DoorFlags": null,
                    "KeyID": -1,
                    "Destination": 25161
                }
            ],
            "ExtraDescs": null
        },
        {
            "ID": 25161,
            "Zone": 251,
            "Name": "Aboard the Chaos ship.",
            "Description": "Two large overhead lamps provide the light for this room. Soot covers the floor\r\r\r\r\n\rwith foot prints going into and out of the room. Stagnate air assualts your\r\r\r\r\n\rsenses as you step into the room. Busted hoses and pipes spray steam and smoke\r\r\r\r\n\rinto the room. \r\r\r\r\n\r",
            "Bits": [
                "INDOORS",
                "NOTELEPORT",
                "NORELOCATE",
                "NOQUIT"
            ],
            "Sector": "INSIDE",
            "Exits": [
                {
                    "Direction": "South",
                    "Description": "",
                    "Keywords": [],
                    "DoorFlags": null,
                    "KeyID": -1,
                    "Destination": 25157
                },
                {
                    "Direction": "West",
                    "Description": "",
                    "Keywords": [],
                    "DoorFlags": null,
                    "KeyID": -1,
                    "Destination": 25160
                }
            ],
            "ExtraDescs": null
        },
        {
            "ID": 25162,
            "Zone": 251,
            "Name": "Aboard the Chaos ship.",
            "Description": "Two large overhead lamps provide the light for this room. Soot covers the floor\r\r\r\r\n\rwith foot prints going into and out of the room. The air in this room is so\r\r\r\r\n\rthin you can hardly breathe. Busted hoses and pipes spray steam and smoke into\r\r\r\r\n\rthe room. \r\r\r\r\n\r",
            "Bits": [
                "INDOORS",
                "NOTELEPORT",
                "NORELOCATE",
                "NOQUIT"
            ],
            "Sector": "INSIDE",
            "Exits": [
                {
                    "Direction": "South",
                    "Description": "",
                    "Keywords": [],
                    "DoorFlags": null,
                    "KeyID": -1,
                    "Destination": 25159
                },
                {
                    "Direction": "Northeast",
                    "Description": "",
                    "Keywords": [],
                    "DoorFlags": null,
                    "KeyID": -1,
                    "Destination": 25164
                }
            ],
            "ExtraDescs": null
        },
        {
            "ID": 25163,
            "Zone": 251,
            "Name": "Aboard the Chaos ship.",
            "Description": "Small flood lights pour light into this room leaving no trace of shadows. Steel\r\r\r\r\n\rgrates line the floor, some like as if they have been eaten through by acid.\r\r\r\r\n\rThe heat in this room is unbelievable. The walls shimmer infront of you from\r\r\r\r\n\rthe heat. Busted hoses and pipes spray steam and smoke into the room. \r\r\r\r\n\r",
            "Bits": [
                "INDOORS",
                "NOTELEPORT",
                "NORELOCATE",
                "NOQUIT"
            ],
            "Sector": "INSIDE",
            "Exits": [
                {
                    "Direction": "North",
                    "Description": "",
                    "Keywords": [],
                    "DoorFlags": null,
                    "KeyID": -1,
                    "Destination": 25166
                },
                {
                    "Direction": "South",
                    "Description": "",
                    "Keywords": [],
                    "DoorFlags": null,
                    "KeyID": -1,
                    "Destination": 25160
                }
            ],
            "ExtraDescs": null
        },
        {
            "ID": 25164,
            "Zone": 251,
            "Name": "Aboard the Chaos ship.",
            "Description": "Two large overhead lamps provide the light for this room. Steel grates line the\r\r\r\r\n\rfloor, some like as if they have been eaten through by acid. Cold air blasts\r\r\r\r\n\ryour face as it streams out of a busted pipe. Green slime drips from the walls\r\r\r\r\n\reating it's way through the floor as it hits. \r\r\r\r\n\r",
            "Bits": [
                "INDOORS",
                "NOTELEPORT",
                "NORELOCATE",
                "NOQUIT"
            ],
            "Sector": "INSIDE",
            "Exits": [
                {
                    "Direction": "North",
                    "Description": "",
                    "Keywords": [],
                    "DoorFlags": null,
                    "KeyID": -1,
                    "Destination": 25169
                },
                {
                    "Direction": "Southwest",
                    "Description": "",
                    "Keywords": [],
                    "DoorFlags": null,
                    "KeyID": -1,
                    "Destination": 25162
                }
            ],
            "ExtraDescs": null
        },
        {
            "ID": 25165,
            "Zone": 251,
            "Name": "Aboard the Chaos ship.",
            "Description": "Small flood lights pour light into this room leaving no trace of shadows. Steel\r\r\r\r\n\rgrates line the floor, some like as if they have been eaten through by acid.\r\r\r\r\n\rCold air blasts your face as it streams out of a busted pipe. Demonic faces\r\r\r\r\n\rand pagan carvings can be seen on all the walls in this room. \r\r\r\r\n\r",
            "Bits": [
                "INDOORS",
                "NOTELEPORT",
                "NORELOCATE",
                "NOQUIT"
            ],
            "Sector": "INSIDE",
            "Exits": [
                {
                    "Direction": "North",
                    "Description": "",
                    "Keywords": [],
                    "DoorFlags": null,
                    "KeyID": -1,
                    "Destination": 25170
                },
                {
                    "Direction": "East",
                    "Description": "",
                    "Keywords": [],
                    "DoorFlags": null,
                    "KeyID": -1,
                    "Destination": 25166
                }
            ],
            "ExtraDescs": null
        },
        {
            "ID": 25166,
            "Zone": 251,
            "Name": "Aboard the Chaos ship.",
            "Description": "Two large overhead lamps provide the light for this room. Steel grates line the\r\r\r\r\n\rfloor, some like as if they have been eaten through by acid. The heat in this\r\r\r\r\n\rroom is unbelievable. The walls shimmer infront of you from the heat. Busted\r\r\r\r\n\rhoses and pipes spray steam and smoke into the room. \r\r\r\r\n\r",
            "Bits": [
                "INDOORS",
                "NOTELEPORT",
                "NORELOCATE",
                "NOQUIT"
            ],
            "Sector": "INSIDE",
            "Exits": [
                {
                    "Direction": "West",
                    "Description": "",
                    "Keywords": [],
                    "DoorFlags": null,
                    "KeyID": -1,
                    "Destination": 25165
                }
            ],
            "ExtraDescs": null
        },
        {
            "ID": 25167,
            "Zone": 251,
            "Name": "Aboard the Chaos ship.",
            "Description": "Two large overhead lamps provide the light for this room. Bodies of Imperial\r\r\r\r\n\rspace marines lay strewn across the floor. Cold air blasts your face as it\r\r\r\r\n\rstreams out of a busted pipe. Demonic faces and pagan carvings can be seen on\r\r\r\r\n\rall the walls in this room. \r\r\r\r\n\r",
            "Bits": [
                "INDOORS",
                "NOTELEPORT",
                "NORELOCATE",
                "NOQUIT"
            ],
            "Sector": "INSIDE",
            "Exits": [
                {
                    "Direction": "East",
                    "Description": "",
                    "Keywords": [],
                    "DoorFlags": null,
                    "KeyID": -1,
                    "Destination": 25168
                }
            ],
            "ExtraDescs": null
        },
        {
            "ID": 25168,
            "Zone": 251,
            "Name": "Aboard the Chaos ship.",
            "Description": "Two large overhead lamps provide the light for this room. Steel grates line the\r\r\r\r\n\rfloor, some like as if they have been eaten through by acid. The heat in this\r\r\r\r\n\rroom is unbelievable. The walls shimmer infront of you from the heat.\r\r\r\r\n\rBulkheads can be seen above you scared and seared as if a huge battle took\r\r\r\r\n\rplace here. \r\r\r\r\n\r",
            "Bits": [
                "INDOORS",
                "NOTELEPORT",
                "NORELOCATE",
                "NOQUIT"
            ],
            "Sector": "INSIDE",
            "Exits": [
                {
                    "Direction": "East",
                    "Description": "",
                    "Keywords": [],
                    "DoorFlags": null,
                    "KeyID": -1,
                    "Destination": 25169
                },
                {
                    "Direction": "West",
                    "Description": "",
                    "Keywords": [],
                    "DoorFlags": null,
                    "KeyID": -1,
                    "Destination": 25167
                }
            ],
            "ExtraDescs": null
        },
        {
            "ID": 25169,
            "Zone": 251,
            "Name": "Aboard the Chaos ship.",
            "Description": "Two large overhead lamps provide the light for this room. Steel grates line the\r\r\r\r\n\rfloor, some like as if they have been eaten through by acid. Cold air blasts\r\r\r\r\n\ryour face as it streams out of a busted pipe. Yellow caution stripes can be\r\r\r\r\n\rseen on the walls with hoses and tubes. \r\r\r\r\n\r",
            "Bits": [
                "INDOORS",
                "NOTELEPORT",
                "NORELOCATE",
                "NOQUIT"
            ],
            "Sector": "INSIDE",
            "Exits": [
                {
                    "Direction": "North",
                    "Description": "",
                    "Keywords": [],
                    "DoorFlags": null,
                    "KeyID": -1,
                    "Destination": 25171
                },
                {
                    "Direction": "South",
                    "Description": "",
                    "Keywords": [],
                    "DoorFlags": null,
                    "KeyID": -1,
                    "Destination": 25164
                },
                {
                    "Direction": "West",
                    "Description": "",
                    "Keywords": [],
                    "DoorFlags": null,
                    "KeyID": -1,
                    "Destination": 25168
                }
            ],
            "ExtraDescs": null
        },
        {
            "ID": 25170,
            "Zone": 251,
            "Name": "Aboard the Chaos ship.",
            "Description": "Flashing yellow lights line this corridor accompanied by loud sirens. Steel\r\r\r\r\n\rgrates line the floor, some like as if they have been eaten through by acid.\r\r\r\r\n\rThe heat in this room is unbelievable. The walls shimmer infront of you from\r\r\r\r\n\rthe heat. Green slime drips from the walls eating it's way through the floor\r\r\r\r\n\ras it hits. \r\r\r\r\n\r",
            "Bits": [
                "INDOORS",
                "NOTELEPORT",
                "NORELOCATE",
                "NOQUIT"
            ],
            "Sector": "INSIDE",
            "Exits": [
                {
                    "Direction": "South",
                    "Description": "",
                    "Keywords": [],
                    "DoorFlags": null,
                    "KeyID": -1,
                    "Destination": 25165
                },
                {
                    "Direction": "Northeast",
                    "Description": "",
                    "Keywords": [],
                    "DoorFlags": null,
                    "KeyID": -1,
                    "Destination": 25172
                }
            ],
            "ExtraDescs": null
        },
        {
            "ID": 25171,
            "Zone": 251,
            "Name": "Aboard the Chaos ship.",
            "Description": "Power must be shut off from this section of the ship because there are no light\r\r\r\r\n\rsources in this room. Soot covers the floor with foot prints going into and\r\r\r\r\n\rout of the room. The air here smells like sulfur and your eyes can not stop\r\r\r\r\n\rfrom watering. Busted hoses and pipes spray steam and smoke into the room. \r\r\r\r\n\r",
            "Bits": [
                "INDOORS",
                "NOTELEPORT",
                "NORELOCATE",
                "NOQUIT"
            ],
            "Sector": "INSIDE",
            "Exits": [
                {
                    "Direction": "South",
                    "Description": "",
                    "Keywords": [],
                    "DoorFlags": null,
                    "KeyID": -1,
                    "Destination": 25169
                },
                {
                    "Direction": "Northwest",
                    "Description": "This hatchway leads to... \r\r\r\r\n\r",
                    "Keywords": [
                        "Hatchway"
                    ],
                    "DoorFlags": [
                        "NORMAL"
                    ],
                    "KeyID": -1,
                    "Destination": 25173
                }
            ],
            "ExtraDescs": null
        },
        {
            "ID": 25172,
            "Zone": 251,
            "Name": "Aboard the Chaos ship.",
            "Description": "Two large overhead lamps provide the light for this room. Soot covers the floor\r\r\r\r\n\rwith foot prints going into and out of the room. Busted hoses and pipes spray\r\r\r\r\n\rsteam and smoke into the room. Stagnate air assualts your senses as you step\r\r\r\r\n\rinto the room. \r\r\r\r\n\r",
            "Bits": [
                "INDOORS",
                "NOTELEPORT",
                "NORELOCATE",
                "NOQUIT"
            ],
            "Sector": "INSIDE",
            "Exits": [
                {
                    "Direction": "Northeast",
                    "Description": "",
                    "Keywords": [],
                    "DoorFlags": null,
                    "KeyID": -1,
                    "Destination": 25174
                },
                {
                    "Direction": "Southwest",
                    "Description": "",
                    "Keywords": [],
                    "DoorFlags": null,
                    "KeyID": -1,
                    "Destination": 25170
                }
            ],
            "ExtraDescs": null
        },
        {
            "ID": 25173,
            "Zone": 251,
            "Name": "Aboard the Chaos ship.",
            "Description": "Two large overhead lamps provide the light for this room. Steel grates line the\r\r\r\r\n\rfloor, some like as if they have been eaten through by acid. The heat in this\r\r\r\r\n\rroom is unbelievable. The walls shimmer infront of you from the heat.\r\r\r\r\n\rBulkheads can be seen above you scared and seared as if a huge battle took\r\r\r\r\n\rplace here. \r\r\r\r\n\r",
            "Bits": [
                "INDOORS",
                "NOTELEPORT",
                "NORELOCATE",
                "NOQUIT"
            ],
            "Sector": "INSIDE",
            "Exits": [
                {
                    "Direction": "Southeast",
                    "Description": "",
                    "Keywords": [],
                    "DoorFlags": null,
                    "KeyID": -1,
                    "Destination": 25171
                }
            ],
            "ExtraDescs": null
        },
        {
            "ID": 25174,
            "Zone": 251,
            "Name": "Aboard the Chaos ship.",
            "Description": "Power must be shut off from this section of the ship because there are no light\r\r\r\r\n\rsources in this room. Small port holes let you look out into the high\r\r\r\r\n\ratomsphere of Macragge. Stagnate air assualts your senses as you step into the\r\r\r\r\n\rroom. Green slime drips from the walls eating it's way through the floor as it\r\r\r\r\n\rhits. \r\r\r\r\n\r",
            "Bits": [
                "INDOORS",
                "NOTELEPORT",
                "NORELOCATE",
                "NOQUIT"
            ],
            "Sector": "INSIDE",
            "Exits": [
                {
                    "Direction": "North",
                    "Description": "This hatchway leads to... \r\r\r\r\n\r",
                    "Keywords": [
                        "Hatchway"
                    ],
                    "DoorFlags": [
                        "NORMAL"
                    ],
                    "KeyID": -1,
                    "Destination": 25175
                },
                {
                    "Direction": "Southwest",
                    "Description": "",
                    "Keywords": [],
                    "DoorFlags": null,
                    "KeyID": -1,
                    "Destination": 25172
                }
            ],
            "ExtraDescs": null
        },
        {
            "ID": 25175,
            "Zone": 251,
            "Name": "Aboard the Chaos ship.",
            "Description": "Small flood lights pour light into this room leaving no trace of shadows.\r\r\r\r\n\rBodies of Imperial space marines lay strewn across the floor. The air in this\r\r\r\r\n\rroom is so thin you can hardly breathe. Green slime drips from the walls\r\r\r\r\n\reating it's way through the floor as it hits. \r\r\r\r\n\r",
            "Bits": [
                "INDOORS",
                "NOTELEPORT",
                "NORELOCATE",
                "NOQUIT"
            ],
            "Sector": "INSIDE",
            "Exits": [
                {
                    "Direction": "South",
                    "Description": "",
                    "Keywords": [],
                    "DoorFlags": null,
                    "KeyID": -1,
                    "Destination": 25174
                }
            ],
            "ExtraDescs": null
        },
        {
            "ID": 25176,
            "Zone": 251,
            "Name": "Aboard the Chaos ship.",
            "Description": "Power must be shut off from this section of the ship because there are no light\r\r\r\r\n\rsources in this room. Soot covers the floor with foot prints going into and\r\r\r\r\n\rout of the room. The air here smells like sulfur and your eyes can not stop\r\r\r\r\n\rfrom watering. Yellow caution stripes can be seen on the walls with hoses and\r\r\r\r\n\rtubes. \r\r\r\r\n\r",
            "Bits": [
                "INDOORS"
            ],
            "Sector": "INSIDE",
            "Exits": null,
            "ExtraDescs": null
        },
        {
            "ID": 25177,
            "Zone": 251,
            "Name": "",
            "Description": "Flashing yellow lights line this corridor accompanied by loud sirens. Steel\r\r\r\r\n\rgrates line the floor, some like as if they have been eaten through by acid.\r\r\r\r\n\rThe heat in this room is unbelievable. The walls shimmer infront of you from\r\r\r\r\n\rthe heat. Demonic faces and pagan carvings can be seen on all the walls in\r\r\r\r\n\rthis room. \r\r\r\r\n\r",
            "Bits": [],
            "Sector": "INSIDE",
            "Exits": null,
            "ExtraDescs": null
        },
        {
            "ID": 25199,
            "Zone": 251,
            "Name": "Aboard the Chaos ship.",
            "Description": "\r",
            "Bits": [],
            "Sector": "INSIDE",
            "Exits": null,
            "ExtraDescs": null
        }
    ]
}